synchronized关键字在Java中用于实现线程同步，确保同一时间只有一个线程可以执行同步代码块或方法。它的底层实现依赖于JVM和操作系统提供的锁机制。
### 1.**Monitor（监视器）机制**
synchronized的底层实现依赖于一个称为“监视器”（Monitor）的机制。每个对象在Java中都有一个与之关联的监视器锁（Monitor Lock）。当一个线程进入一个synchronized方法或代码块时，它会尝试获取该对象的监视器锁。
### 2.**JVM指令**
synchronized关键字会被编译器转换为字节码中的两条指令：monitorenter和monitorexit。

- **monitorenter**：当线程进入同步方法或代码块时，尝试获取对象的监视器锁。如果锁已经被其他线程持有，当前线程会被阻塞，直到锁被释放。
- **monitorexit**：当线程退出同步方法或代码块时，释放对象的监视器锁。
### 3.**对象头（Object Header）**
在HotSpot JVM中，对象头（Object Header）包含了锁信息。对象头中有一个Mark Word（标记字段），用于存储锁状态和其他信息。锁可以有多种状态，主要包括以下几种：

- **无锁（Unlocked）**：对象没有被任何线程持有锁。
- **偏向锁（Biased Locking）**：一个线程偏向于持有锁，减少了加锁和解锁的开销。
- **轻量级锁（Lightweight Locking）**：通过CAS（Compare-And-Swap）操作实现的锁，适用于低竞争的场景。
- **重量级锁（Heavyweight Locking）**：通过操作系统的互斥量（Mutex）实现的锁，适用于高竞争的场景。
### 4.**锁的升级**
JVM会根据竞争情况在不同的锁状态之间进行升级

- **偏向锁**：默认情况下，JVM会尝试使用偏向锁，当一个线程多次进入同步块时，不需要每次都进行加锁操作。
- **轻量级锁**：如果有多个线程竞争同一个锁，偏向锁会升级为轻量级锁。
- **重量级锁**：如果锁竞争激烈，轻量级锁会升级为重量级锁。
### 5.**锁消除和锁粗化**
JVM在运行时会进行一些优化来减少锁的开销：

- **锁消除（Lock Elimination）**：JVM在JIT编译时会分析代码，如果发现某些锁是多余的（如局部变量锁），会自动消除这些锁。
- **锁粗化（Lock Coarsening）**：JVM会将多个连续的加锁和解锁操作合并为一个更大的加锁操作，减少锁的开销。
### 6.**具体实现细节**

```
public class SynchronizedExample {


    public synchronized void increment() {
        count++;
    }
}
```
编译后的字节码（使用javap -c命令查看）：
```
public synchronized void increment();
    Code:
       0: aload_0
       1: dup
       2: astore_1
       3: monitorenter
       4: aload_0
       5: aload_0
       6: getfield      #2                  // Field count:I
       9: iconst_1
      10: iadd
      11: putfield      #2                  // Field count:I
      14: aload_1
      15: monitorexit
      16: goto          24
      19: astore_2
      20: aload_1
      21: monitorexit
      22: aload_2
      23: athrow
      24: return
```
synchronized方法被编译为monitorenter和monitorexit指令，确保在方法开始时获取锁，在方法结束时释放锁。
### 总结
synchronized的底层实现依赖于JVM的监视器机制，通过对象头中的Mark Word来管理锁状态，并通过monitorenter和monitorexit指令来实现加锁和解锁。
